flake8_vedro_allure_id_plugin/__init__.py
flake8_vedro_allure_id_plugin/plugin.py
tests/__init__.py
tests/test_plugin.py
flake8_vedro_allure_id-0.1.0.dist-info/METADATA
flake8_vedro_allure_id-0.1.0.dist-info/WHEEL
flake8_vedro_allure_id-0.1.0.dist-info/entry_points.txt
flake8_vedro_allure_id-0.1.0.dist-info/top_level.txt
flake8_vedro_allure_id-0.1.0.dist-info/RECORD
